odoo10_addon_account_cutoff_accrual_dates-10.0.1.1.0-py2.7-nspkg.pth
odoo/addons/account_cutoff_accrual_dates/README.rst
odoo/addons/account_cutoff_accrual_dates/__init__.py
odoo/addons/account_cutoff_accrual_dates/__manifest__.py
odoo/addons/account_cutoff_accrual_dates/models/__init__.py
odoo/addons/account_cutoff_accrual_dates/models/account_cutoff.py
odoo10_addon_account_cutoff_accrual_dates-10.0.1.1.0.dist-info/DESCRIPTION.rst
odoo10_addon_account_cutoff_accrual_dates-10.0.1.1.0.dist-info/METADATA
odoo10_addon_account_cutoff_accrual_dates-10.0.1.1.0.dist-info/RECORD
odoo10_addon_account_cutoff_accrual_dates-10.0.1.1.0.dist-info/WHEEL
odoo10_addon_account_cutoff_accrual_dates-10.0.1.1.0.dist-info/metadata.json
odoo10_addon_account_cutoff_accrual_dates-10.0.1.1.0.dist-info/namespace_packages.txt
odoo10_addon_account_cutoff_accrual_dates-10.0.1.1.0.dist-info/top_level.txt
